pynasafirms/__init__.py
pynasafirms/pynasafirms.py
pynasafirms-0.0.1.dist-info/METADATA
pynasafirms-0.0.1.dist-info/WHEEL
pynasafirms-0.0.1.dist-info/licenses/LICENSE
pynasafirms-0.0.1.dist-info/RECORD
