Metadata-Version: 2.1
Name: pynasafirms
Version: 0.0.1
Summary: A package for querying NASA's FIRMS
Project-URL: Homepage, https://github.com/PlantDaddy/pyNASAFIRMS
Project-URL: Bug Tracker, https://github.com/PlantDaddy/pyNASAFIRMS/issues
Author-email: PlantDaddy <CqP5TZ77NYBf5uQt@protonmail.com>
License:                     GNU AFFERO GENERAL PUBLIC LICENSE
License-File: LICENSE
Classifier: License :: OSI Approved :: GNU Affero General Public License v3
Classifier: Operating System :: OS Independent
Classifier: Programming Language :: Python :: 3
Requires-Python: >=3.7
